{
	"format_version": "1.8.0",
	"geometry.skeleton42.v1.8": {
		"texturewidth": 160,
		"textureheight": 96,
		"visible_bounds_width": 3,
		"visible_bounds_height": 3,
		"visible_bounds_offset": [0, 1.5, 0],
		"bones": [
			{
				"name": "waist",
				"pivot": [0, 12, 0]
			},
			{
				"name": "body",
				"parent": "waist",
				"pivot": [0, 24, 0]
			},
			{
				"name": "head",
				"parent": "body",
				"pivot": [0, 24, 0]
			},
			{
				"name": "head2",
				"parent": "head",
				"pivot": [0, 24, 0]
			},
			{
				"name": "piglin_head",
				"parent": "head2",
				"pivot": [0, 24, 0],
				"cubes": [
					{"origin": [-5, 24, -4], "size": [10, 8, 8], "uv": [0, 0]},
					{"origin": [-5, 24, -4], "size": [10, 8, 8], "uv": [46, 0], "inflate": 0.25}
				]
			},
			{
				"name": "piglin_nose",
				"parent": "piglin_head",
				"pivot": [0, 0, 0],
				"cubes": [
					{"origin": [-2, 24, -5], "size": [4, 4, 1], "uv": [31, 1], "inflate": 0.01},
					{"origin": [-3, 24, -5], "size": [1, 2, 1], "uv": [2, 4]},
					{"origin": [2, 24, -5], "size": [1, 2, 1], "uv": [2, 0]}
				]
			},
			{
				"name": "ear1",
				"parent": "piglin_head",
				"pivot": [-4, 30, 0],
				"rotation": [0, 0, 30],
				"cubes": [
					{"origin": [-5, 25, -2], "size": [1, 5, 4], "uv": [36, 7]}
				]
			},
			{
				"name": "ear2",
				"parent": "piglin_head",
				"pivot": [4, 30, 0],
				"rotation": [0, 0, -30],
				"cubes": [
					{"origin": [4, 25, -2], "size": [1, 5, 4], "uv": [36, 7]}
				]
			},
			{
				"name": "dripstone_head",
				"parent": "piglin_head",
				"pivot": [0, 0, 0],
				"cubes": [
					{"origin": [-4.5, 24, -4], "size": [9, 8, 8], "uv": [82, 0], "inflate": -0.2},
					{"origin": [1, 21, -5.02], "size": [1, 4, 0], "uv": [101, 19]}
				]
			},
			{
				"name": "dripstone_mohawk",
				"parent": "dripstone_head",
				"pivot": [0, 0, 0],
				"cubes": [
					{"origin": [0, 24, -9], "size": [0, 15, 18], "uv": [80, 31]}
				]
			},
			{
				"name": "rightArm",
				"parent": "body",
				"pivot": [-5, 22, 0]
			},
			{
				"name": "rightItem",
				"parent": "rightArm",
				"pivot": [-6, 15, 1]
			},
			{
				"name": "right_arm",
				"parent": "rightArm",
				"pivot": [-5, 22, 0],
				"cubes": [
					{"origin": [-8, 12, -2], "size": [4, 12, 4], "uv": [64, 48], "inflate": 0.1}
				]
			},
			{
				"name": "piglin_right_arm",
				"parent": "right_arm",
				"pivot": [0, 0, 0],
				"cubes": [
					{"origin": [-7, 12, -1.5], "size": [3, 12, 3], "uv": [40, 49]}
				]
			},
			{
				"name": "leftArm",
				"parent": "body",
				"pivot": [5, 22, 0],
				"mirror": true
			},
			{
				"name": "leftItem",
				"parent": "leftArm",
				"pivot": [6, 15, 1]
			},
			{
				"name": "left_arm",
				"parent": "leftArm",
				"pivot": [5, 22, 0],
				"mirror": true,
				"cubes": [
					{"origin": [4, 12, -2], "size": [4, 12, 4], "uv": [64, 48], "inflate": 0.1}
				]
			},
			{
				"name": "piglin_left_arm",
				"parent": "left_arm",
				"pivot": [0, 0, -0.5],
				"mirror": true,
				"cubes": [
					{"origin": [4, 12, -1.5], "size": [3, 12, 3], "uv": [40, 49]}
				]
			},
			{
				"name": "rightLeg",
				"parent": "body",
				"pivot": [-2, 12, 0]
			},
			{
				"name": "right_leg",
				"parent": "rightLeg",
				"pivot": [-2, 12, 0.1]
			},
			{
				"name": "piglin_right_leg",
				"parent": "right_leg",
				"pivot": [0, 0, 0],
				"cubes": [
					{"origin": [-3.5, 0, -1.5], "size": [3, 12, 3], "uv": [52, 49]}
				]
			},
			{
				"name": "leftLeg",
				"parent": "body",
				"pivot": [2, 12, 0],
				"mirror": true
			},
			{
				"name": "left_leg",
				"parent": "leftLeg",
				"pivot": [2, 12, 0.1],
				"mirror": true
			},
			{
				"name": "piglin_left_leg",
				"parent": "left_leg",
				"pivot": [0, 0, 0],
				"mirror": true,
				"cubes": [
					{"origin": [0.5, 0, -1.5], "size": [3, 12, 3], "uv": [52, 49]}
				]
			},
			{
				"name": "body2",
				"parent": "body",
				"pivot": [0, 24, 0],
				"cubes": [
					{"origin": [-4, 3, -2.5], "size": [8, 21, 5], "uv": [52, 16], "inflate": 0.01}
				]
			},
			{
				"name": "piglin_body",
				"parent": "body2",
				"pivot": [0, 0, 0],
				"cubes": [
					{"origin": [-4, 12, -2.5], "size": [8, 12, 5], "uv": [0, 16]},
					{"origin": [-4, 12, -2.5], "size": [8, 12, 5], "uv": [26, 16], "inflate": 0.25}
				]
			},
			{
				"name": "piglin_quiver_rotation",
				"parent": "piglin_body",
				"pivot": [0, 18, -0.5],
				"rotation": [0, 0, -45]
			},
			{
				"name": "piglin_quiver",
				"parent": "piglin_quiver_rotation",
				"pivot": [-0.20577, -0.35641, -0.5],
				"cubes": [
					{"origin": [-3.20577, 11.64359, 2.6], "size": [6, 12, 4], "uv": [20, 48]},
					{"origin": [-3.20577, 11.64359, 2.6], "size": [6, 12, 4], "uv": [0, 48], "inflate": 0.25}
				]
			},
			{
				"name": "piglin_arrow",
				"parent": "piglin_quiver",
				"pivot": [-0.20577, -0.35641, -1],
				"cubes": [
					{"origin": [0.79423, 23.64359, 1.6], "size": [0, 7, 5], "uv": [0, 28]},
					{"origin": [-1.70577, 23.64359, 4.1], "size": [5, 7, 0], "uv": [0, 33]}
				]
			},
			{
				"name": "piglin_arrow2",
				"parent": "piglin_quiver",
				"pivot": [5.79423, 0.64359, -1],
				"rotation": [0, 0, -12.5],
				"cubes": [
					{"origin": [1.29423, 22.64359, 5.1], "size": [5, 7, 0], "uv": [0, 33]},
					{"origin": [3.79423, 22.64359, 2.6], "size": [0, 7, 5], "uv": [0, 28]}
				]
			},
			{
				"name": "piglin_arrow3",
				"parent": "piglin_quiver",
				"pivot": [-4.20577, 1.64359, -4],
				"rotation": [-7.5, 0, 20],
				"cubes": [
					{"origin": [-8.70577, 23.64359, 2.1], "size": [5, 7, 0], "uv": [0, 33]},
					{"origin": [-6.20577, 23.64359, -0.4], "size": [0, 7, 5], "uv": [0, 28]}
				]
			},
			{
				"name": "dripstone_body",
				"parent": "body2",
				"pivot": [0, 0, 0],
				"cubes": [
					{"origin": [-4, 12.5, -2], "size": [8, 1, 4], "uv": [92, 30], "inflate": -0.1},
					{"origin": [-2, 13, 0], "size": [1, 11, 0], "uv": [107, 17]}
				]
			}
		]
	}
}